[
  {
    "Тип": "Состояние здоровья",
    "Имя": "Крепость в теле",
    "Описание": "Общее физическое укрепление, ощущение силы и выносливости, которое автор часто отмечает, особенно после занятий гимнастикой, плавания или физического труда.",
    "Упоминания": [
      {
        "Номер строки": 2,
        "Роль": "Сильное влияние гимнастики на мускулы"
      },
      {
        "Номер строки": 21,
        "Роль": "Начало правильного купания"
      },
      {
        "Номер строки": 394,
        "Роль": "Тело становится видимо крепче"
      },
      {
        "Номер строки": 395,
        "Роль": "Исчезновение боли в пояснице"
      },
      {
        "Номер строки": 423,
        "Роль": "Ощущение крепости и силы"
      },
      {
        "Номер строки": 424,
        "Роль": "Воспоминание о хорошей работе и крепком сне"
      },
      {
        "Номер строки": 432,
        "Роль": "Отличное ощущение силы в плечах, спине и ногах"
      },
      {
        "Номер строки": 435,
        "Роль": "Чувство мощи"
      },
      {
        "Номер строки": 452,
        "Роль": "Чувство крепости в течение всего дня"
      },
      {
        "Номер строки": 468,
        "Роль": "Ощущение легкости и благостности"
      },
      {
        "Номер строки": 486,
        "Роль": "Тело гиминастиковое, упругое на ощупь"
      },
      {
        "Номер строки": 503,
        "Роль": "Ощущение слабости, но без тяжелой дремоты"
      },
      {
        "Номер строки": 513,
        "Роль": "Тело крепко, ощущение жара в теле"
      },
      {
        "Номер строки": 514,
        "Роль": "Причина крепости — раннее вхождение в воду"
      },
      {
        "Номер строки": 517,
        "Роль": "Чувство силы в оплечьях"
      },
      {
        "Номер строки": 525,
        "Роль": "Ощущение крепнущего тела"
      },
      {
        "Номер строки": 526,
        "Роль": "Ощутимая крепость силы и упругость мышц"
      },
      {
        "Номер строки": 535,
        "Роль": "Тело крепко"
      },
      {
        "Номер строки": 539,
        "Роль": "Отсутствие усталости"
      },
      {
        "Номер строки": 560,
        "Роль": "Отсутствие усталости после ходьбы"
      },
      {
        "Номер строки": 562,
        "Роль": "Крепость в ногах"
      },
      {
        "Номер строки": 567,
        "Роль": "Отличное самочувствие несмотря на холеру"
      },
      {
        "Номер строки": 573,
        "Роль": "Значительная сила"
      },
      {
        "Номер строки": 591,
        "Роль": "Возвращение в хорошем состоянии после прогулки"
      },
      {
        "Номер строки": 606,
        "Роль": "Чувство закованности, особенно в ногах, после гребли"
      },
      {
        "Номер строки": 607,
        "Роль": "Довольство собой"
      },
      {
        "Номер строки": 638,
        "Роль": "Начало гимнастики после ревматизма, обнаружение прироста силы"
      },
      {
        "Номер строки": 639,
        "Роль": "Хорошее самочувствие"
      },
      {
        "Номер строки": 640,
        "Роль": "Положительное состояние"
      },
      {
        "Номер строки": 646,
        "Роль": "Положительное состояние, ноги горят"
      },
      {
        "Номер строки": 651,
        "Роль": "Хорошее, свежее самочувствие"
      },
      {
        "Номер строки": 656,
        "Роль": "Среднее состояние на ходу"
      },
      {
        "Номер строки": 666,
        "Роль": "Тело горит после гимнастики"
      },
      {
        "Номер строки": 687,
        "Роль": "Положительное состояние в течение нескольких дней"
      },
      {
        "Номер строки": 688,
        "Роль": "Свежесть и крепость"
      },
      {
        "Номер строки": 692,
        "Роль": "Хорошее самочувствие после легкой еды"
      },
      {
        "Номер строки": 696,
        "Роль": "Свежесть"
      },
      {
        "Номер строки": 706,
        "Роль": "Успехи в гимнастике"
      },
      {
        "Номер строки": 708,
        "Роль": "Умение прыгать через лошадь"
      },
      {
        "Номер строки": 710,
        "Роль": "Отличное самочувствие вечером"
      },
      {
        "Номер строки": 712,
        "Роль": "Победа в борьбе с Пуаре, крепкий сон"
      },
      {
        "Номер строки": 713,
        "Роль": "Сильное пробуждение"
      },
      {
        "Номер строки": 718,
        "Роль": "Довольно сильное самочувствие"
      },
      {
        "Номер строки": 722,
        "Роль": "Сильное самочувствие, хорошие прыжки"
      },
      {
        "Номер строки": 728,
        "Роль": "Укрепление от гимнастики"
      },
      {
        "Номер строки": 729,
        "Роль": "Сила, кажется, сильнее лета"
      },
      {
        "Номер строки": 730,
        "Роль": "Отличное физическое состояние"
      },
      {
        "Номер строки": 794,
        "Роль": "Весьма хорошее физическое состояние"
      },
      {
        "Номер строки": 795,
        "Роль": "Освежительное действие столярничества"
      },
      {
        "Номер строки": 798,
        "Роль": "Много силы, тело полно, сложение хорошо"
      },
      {
        "Номер строки": 799,
        "Роль": "Положительное состояние"
      },
      {
        "Номер строки": 802,
        "Роль": "Тело крепче чем когда-либо, чрезвычайная легкость"
      },
      {
        "Номер строки": 834,
        "Роль": "Весьма сильное самочувствие после охоты"
      },
      {
        "Номер строки": 838,
        "Роль": "Чувство силы"
      },
      {
        "Номер строки": 846,
        "Роль": "Чувство силы, отсутствие усталости, крепость в холоду"
      },
      {
        "Номер строки": 851,
        "Роль": "Чрезвычайное укрепление сил от плотничества"
      },
      {
        "Номер строки": 857,
        "Роль": "Чрезвычайная сила как никогда"
      },
      {
        "Номер строки": 860,
        "Роль": "Прибавка в весе на 4 фунта, тело очень крепко"
      },
      {
        "Номер строки": 862,
        "Роль": "Умение хорошо прыгать на лошадь"
      },
      {
        "Номер строки": 877,
        "Роль": "Выполнение упражнения 'bras de fer' в чистоту"
      },
      {
        "Номер строки": 902,
        "Роль": "Отсутствие усталости после охоты"
      },
      {
        "Номер строки": 903,
        "Роль": "Поправление тела от охоты"
      },
      {
        "Номер строки": 929,
        "Роль": "Отличное самочувствие после работы в саду"
      },
      {
        "Номер строки": 940,
        "Роль": "Ощущение крепости и малой лихорадочности"
      },
      {
        "Номер строки": 962,
        "Роль": "Простуда после работы в саду"
      },
      {
        "Номер строки": 995,
        "Роль": "Ощущение силы несмотря на боль"
      },
      {
        "Номер строки": 996,
        "Роль": "Возбуждение организма во всех функциях"
      },
      {
        "Номер строки": 1004,
        "Роль": "Широкое дыхание, сила в членах"
      },
      {
        "Номер строки": 1015,
        "Роль": "Отличная переносимость усталости"
      },
      {
        "Номер строки": 1043,
        "Роль": "Хорошее самочувствие"
      },
      {
        "Номер строки": 1084,
        "Роль": "Отличное самочувствие в полдень"
      },
      {
        "Номер строки": 1087,
        "Роль": "Тяжелое самочувствие, слабость от жары"
      },
      {
        "Номер строки": 1126,
        "Роль": "Теплый день"
      },
      {
        "Номер строки": 1149,
        "Роль": "Выполнение работ по хозяйству"
      },
      {
        "Номер строки": 1192,
        "Роль": "Хорошее действие купания"
      },
      {
        "Номер строки": 1193,
        "Роль": "Отличное физическое состояние вечером"
      },
      {
        "Номер строки": 1198,
        "Роль": "Ощущение крепости"
      },
      {
        "Номер строки": 1199,
        "Роль": "Крепкий сон"
      },
      {
        "Номер строки": 1201,
        "Роль": "Хорошее самочувствие"
      },
      {
        "Номер строки": 1223,
        "Роль": "Ощущение крепости, но мало работы"
      },
      {
        "Номер строки": 1244,
        "Роль": "Здоровое самочувствие"
      },
      {
        "Номер строки": 1246,
        "Роль": "Хороший сон"
      },
      {
        "Номер строки": 1254,
        "Роль": "Хороший сон, пополнение, но мало равновесия"
      },
      {
        "Номер строки": 1274,
        "Роль": "Плохое самочувствие, боли в животе"
      },
      {
        "Номер строки": 1277,
        "Роль": "Нездоровье весь день"
      },
      {
        "Номер строки": 1279,
        "Роль": "Нездоровье"
      },
      {
        "Номер строки": 1288,
        "Роль": "Не совсем здоров, расстроен, сильная хандра"
      },
      {
        "Номер строки": 1293,
        "Роль": "Тоска и хандра"
      },
      {
        "Номер строки": 1298,
        "Роль": "Хороший сон"
      },
      {
        "Номер строки": 1318,
        "Роль": "Хороший сон, старение лица, хороший аппетит, плохая умственная деятельность"
      },
      {
        "Номер строки": 1342,
        "Роль": "Больное горло, насморк"
      },
      {
        "Номер строки": 1349,
        "Роль": "Лучшее самочувствие, хороший сон"
      },
      {
        "Номер строки": 1360,
        "Роль": "Нездоровье вечером"
      },
      {
        "Номер строки": 1362,
        "Роль": "Плохое пробуждение, кашель"
      },
      {
        "Номер строки": 1390,
        "Роль": "Усталость, изможденность, плохой и старый вид"
      },
      {
        "Номер строки": 1392,
        "Роль": "Очень плохое самочувствие"
      },
      {
        "Номер строки": 1408,
        "Роль": "Справившееся лицо, исчезновение морщин, отсутствие хандры"
      },
      {
        "Номер строки": 1459,
        "Роль": "Приезд без усталости"
      },
      {
        "Номер строки": 1461,
        "Роль": "Ощущение себя посильнее, но упавший аппетит"
      },
      {
        "Номер строки": 1467,
        "Роль": "Здоровое самочувствие, значительное пополнение"
      },
      {
        "Номер строки": 1469,
        "Роль": "Поправление здоровья, хотя мало работал летом"
      },
      {
        "Номер строки": 1472,
        "Роль": "Достаточно хорошее самочувствие"
      },
      {
        "Номер строки": 1473,
        "Роль": "Свежесть и бодрость, крепкое тело"
      },
      {
        "Номер строки": 1490,
        "Роль": "Ощущение силы и много силы"
      },
      {
        "Номер строки": 1504,
        "Роль": "Крепкое самочувствие, легкая переносимость дороги"
      },
      {
        "Номер строки": 1506,
        "Роль": "Появление слабости от сигары"
      },
      {
        "Номер строки": 1510,
        "Роль": "Отличный сон"
      },
      {
        "Номер строки": 1524,
        "Роль": "Хороший аппетит"
      },
      {
        "Номер строки": 1554,
        "Роль": "Пешая ходьба крайне полезна"
      },
      {
        "Номер строки": 1637,
        "Роль": "Усталость после ходьбы, хороший аппетит"
      },
      {
        "Номер строки": 1639,
        "Роль": "Ощущение крепости, которого почти год не чувствовал"
      },
      {
        "Номер строки": 1740,
        "Роль": "Отличное самочувствие"
      },
      {
        "Номер строки": 1759,
        "Роль": "Неудачная попытка вымыть тело"
      },
      {
        "Номер строки": 1764,
        "Роль": "Смех до упаду от своей сцены"
      },
      {
        "Номер строки": 1768,
        "Роль": "Хорошая столярная работа"
      },
      {
        "Номер строки": 1774,
        "Роль": "Очень легкая ходьба"
      },
      {
        "Номер строки": 1777,
        "Роль": "Хорошее физическое состояние"
      },
      {
        "Номер строки": 1817,
        "Роль": "Хороший аппетит"
      },
      {
        "Номер строки": 1820,
        "Роль": "Мягкое, зернистое тело, а не плотное"
      },
      {
        "Номер строки": 1821,
        "Роль": "Заметное похудение"
      },
      {
        "Номер строки": 1823,
        "Роль": "Легкая ходьба, но плохое самочувствие"
      },
      {
        "Номер строки": 1825,
        "Роль": "Большая слабость"
      },
      {
        "Номер строки": 1826,
        "Роль": "Внутренняя осень и уныние"
      },
      {
        "Номер строки": 1833,
        "Роль": "Хорошее и здоровое самочувствие весь день"
      },
      {
        "Номер строки": 1844,
        "Роль": "Хорошее пробуждение"
      },
      {
        "Номер строки": 1846,
        "Роль": "Хорошее самочувствие после прогулки"
      },
      {
        "Номер строки": 1847,
        "Роль": "Малое ощущение холода"
      },
      {
        "Номер строки": 1853,
        "Роль": "Отличный сон"
      },
      {
        "Номер строки": 1854,
        "Роль": "Прекрасное, свежее и сильное самочувствие после работы"
      },
      {
        "Номер строки": 1856,
        "Роль": "Лучшая переносимость физического труда"
      },
      {
        "Номер строки": 1857,
        "Роль": "Отсутствие чувства усталости несколько месяцев"
      },
      {
        "Номер строки": 1860,
        "Роль": "Отсутствие усталости от разъездов"
      },
      {
        "Номер строки": 1872,
        "Роль": "Maximum силы в начале лета"
      },
      {
        "Номер строки": 1877,
        "Роль": "Совершенно эластическое тело"
      },
      {
        "Номер строки": 1879,
        "Роль": "Положительный день, кажется maximum"
      },
      {
        "Номер строки": 1880,
        "Роль": "Чувство крепости"
      },
      {
        "Номер строки": 1881,
        "Роль": "Прибывание жизни"
      },
      {
        "Номер строки": 1882,
        "Роль": "Отличный сон"
      },
      {
        "Номер строки": 1893,
        "Роль": "Отличный сон"
      },
      {
        "Номер строки": 1896,
        "Роль": "Необычайно хорошее пробуждение"
      },
      {
        "Номер строки": 1899,
        "Роль": "Нечувствие холода"
      },
      {
        "Номер строки": 1900,
        "Роль": "Чрезвычайно сильное самочувствие, пополнение лица"
      },
      {
        "Номер строки": 1904,
        "Роль": "Отсутствие усталости"
      },
      {
        "Номер строки": 1907,
        "Роль": "Простуда"
      },
      {
        "Номер строки": 1914,
        "Роль": "Простуда в Москве"
      },
      {
        "Номер строки": 1928,
        "Роль": "Хорошее расположение духа"
      },
      {
        "Номер строки": 1931,
        "Роль": "Хорошее расположение духа"
      },
      {
        "Номер строки": 1932,
        "Роль": "Крепкое самочувствие"
      },
      {
        "Номер строки": 1955,
        "Роль": "Плохое здоровье, ревматизм летучий"
      },
      {
        "Номер строки": 1958,
        "Роль": "Плохое и позднее пробуждение"
      },
      {
        "Номер строки": 1966,
        "Роль": "Хорошее пробуждение"
      },
      {
        "Номер строки": 2182,
        "Роль": "Сильные ревматизмы и кашель"
      },
      {
        "Номер строки": 2183,
        "Роль": "Отрицательное состояние"
      }
    ]
  },
  {
    "Тип": "Состояние здоровья",
    "Имя": "Болезнь",
    "Описание": "Общее указание на заболевание или нездоровье, без конкретизации.",
    "Упоминания": [
      {
        "Номер строки": 15,
        "Роль": "Болезнь Прасковьи Александровны"
      },
      {
        "Номер строки": 127,
        "Роль": "Нахождение в бреду"
      },
      {
        "Номер строки": 255,
        "Роль": "Болезнь после скачек"
      },
      {
        "Номер строки": 672,
        "Роль": "Слабость и болезнь до конца месяца"
      },
      {
        "Номер строки": 675,
        "Роль": "Поправление здоровьем после сна дома"
      },
      {
        "Номер строки": 714,
        "Роль": "День Луизы (возможно, связан с ее болезнью или смертью)"
      },
      {
        "Номер строки": 865,
        "Роль": "Начало расстройства здоровьем"
      },
      {
        "Номер строки": 1275,
        "Роль": "Боли в животе"
      },
      {
        "Номер строки": 1348,
        "Роль": "Болезнь герцога Лихтемберского"
      }
    ]
  },
  {
    "Тип": "Состояние здоровья",
    "Имя": "Простуда",
    "Описание": "Состояние, вызванное переохлаждением, часто сопровождающееся кашлем, насморком.",
    "Упоминания": [
      {
        "Номер строки": 25,
        "Роль": "Простуда на лодке"
      },
      {
        "Номер строки": 437,
        "Роль": "Забота о том, чтобы не простудиться"
      },
      {
        "Номер строки": 450,
        "Роль": "Ощущение холода"
      },
      {
        "Номер строки": 962,
        "Роль": "Простуда после работы в саду"
      },
      {
        "Номер строки": 1907,
        "Роль": "Простуда в пути"
      },
      {
        "Номер строки": 1914,
        "Роль": "Простуда в Москве"
      }
    ]
  },
  {
    "Тип": "Состояние здоровья",
    "Имя": "Головная боль",
    "Описание": "Болевые ощущения в голове.",
    "Упоминания": [
      {
        "Номер строки": 536,
        "Роль": "Некоторая головная боль днем"
      },
      {
        "Номер строки": 583,
        "Роль": "Заболела голова от купания в холодной воде"
      },
      {
        "Номер строки": 632,
        "Роль": "Головная боль после лодки"
      },
      {
        "Номер строки": 734,
        "Роль": "Странная головная боль весь день"
      },
      {
        "Номер строки": 774,
        "Роль": "Головная боль, слабость, тяжесть"
      }
    ]
  },
  {
    "Тип": "Состояние здоровья",
    "Имя": "Ревматизм",
    "Описание": "Заболевание суставов и мышц, проявляющееся болями и ломотой.",
    "Упоминания": [
      {
        "Номер строки": 635,
        "Роль": "Ревматические припадки, лом во многих местах"
      },
      {
        "Номер строки": 671,
        "Роль": "Признаки летучего ревматизма"
      },
      {
        "Номер строки": 1956,
        "Роль": "Летучий ревматизм в затылке, межвертелии и правой руке"
      }
    ]
  },
  {
    "Тип": "Состояние здоровья",
    "Имя": "Расстройство желудка (гастрическое)",
    "Описание": "Проблемы с пищеварением, боли в желудке, рвота.",
    "Упоминания": [
      {
        "Номер строки": 255,
        "Роль": "Indigestion (несварение)"
      },
      {
        "Номер строки": 1203,
        "Роль": "Гастрический припадок, боль желудка и рвота"
      },
      {
        "Номер строки": 1204,
        "Роль": "Странная боль желудка и рвота"
      }
    ]
  },
  {
    "Тип": "Состояние здоровья",
    "Имя": "Флюс",
    "Описание": "Воспалительное заболевание десны, обычно с отеком.",
    "Упоминания": [
      {
        "Номер строки": 454,
        "Роль": "Маленький флюс"
      }
    ]
  },
  {
    "Тип": "Состояние здоровья",
    "Имя": "Удушье",
    "Описание": "Затруднение дыхания, приступ удушья.",
    "Упоминания": [
      {
        "Номер строки": 670,
        "Роль": "Припадок удушья ночью"
      }
    ]
  },
  {
    "Тип": "Состояние здоровья",
    "Имя": "Холера",
    "Описание": "Опасное инфекционное заболевание, эпидемия которого упоминается в Москве.",
    "Упоминания": [
      {
        "Номер строки": 566,
        "Роль": "Начало усиления холеры"
      },
      {
        "Номер строки": 567,
        "Роль": "Достижение maximum заболевания"
      },
      {
        "Номер строки": 576,
        "Роль": "Холера произвела панику"
      },
      {
        "Номер строки": 577,
        "Роль": "Заболело 380, умерло 165 человек"
      },
      {
        "Номер строки": 578,
        "Роль": "Много умерших из неимущих"
      },
      {
        "Номер строки": 1257,
        "Роль": "Рецепт от холеры"
      }
    ]
  },
  {
    "Тип": "Состояние здоровья",
    "Имя": "Насморк",
    "Описание": "Воспаление слизистой носа.",
    "Упоминания": [
      {
        "Номер строки": 1342,
        "Роль": "Насморк"
      }
    ]
  },
  {
    "Тип": "Состояние здоровья",
    "Имя": "Боль в горле",
    "Описание": "Болезненные ощущения в горле.",
    "Упоминания": [
      {
        "Номер строки": 1342,
        "Роль": "Болит горло"
      }
    ]
  },
  {
    "Тип": "Состояние здоровья",
    "Имя": "Кашель",
    "Описание": "Рефлекторное действие для очистки дыхательных путей.",
    "Упоминания": [
      {
        "Номер строки": 1362,
        "Роль": "Кашель"
      },
      {
        "Номер строки": 2182,
        "Роль": "Кашель"
      }
    ]
  },
  {
    "Тип": "Состояние здоровья",
    "Имя": "Ослабление чувств",
    "Описание": "Снижение остроты обоняния, зрения, вкуса и аппетита после нервного потрясения.",
    "Упоминания": [
      {
        "Номер строки": 1010,
        "Роль": "Потрясение организма, ослабление нервной функции"
      },
      {
        "Номер строки": 1011,
        "Роль": "Ослабление обоняния и зрения"
      },
      {
        "Номер строки": 1012,
        "Роль": "Ослабление зрения"
      },
      {
        "Номер строки": 1013,
        "Роль": "Ослабление аппетита и вкуса, пропажа аппетита"
      },
      {
        "Номер строки": 1016,
        "Роль": "Умаление эротического ощущения"
      }
    ]
  },
  {
    "Тип": "Состояние здоровья",
    "Имя": "Смерть",
    "Описание": "Летальный исход.",
    "Упоминания": [
      {
        "Номер строки": 16,
        "Роль": "Смерть Прасковьи Александровны"
      },
      {
        "Номер строки": 1285,
        "Роль": "Смерть Сергея Ивановича Толбузина"
      },
      {
        "Номер строки": 1746,
        "Роль": "Смерть Дуду (Луизы)"
      },
      {
        "Номер строки": 2034,
        "Роль": "Смерть мужа Акимовой"
      }
    ]
  },
  {
    "Тип": "Состояние здоровья",
    "Имя": "Психическое состояние",
    "Описание": "Эмоциональное и душевное состояние автора, включая хандру, тоску, уныние, радость, возбуждение.",
    "Упоминания": [
      {
        "Номер строки": 1222,
        "Роль": "Тихо-грустная настроенность"
      },
      {
        "Номер строки": 1230,
        "Роль": "Грустное расположение духа"
      },
      {
        "Номер строки": 1231,
        "Роль": "Не в духе"
      },
      {
        "Номер строки": 1288,
        "Роль": "Расстроен, скучен, сильная хандра"
      },
      {
        "Номер строки": 1293,
        "Роль": "Тоска и хандра"
      },
      {
        "Номер строки": 1311,
        "Роль": "Много тоски на сердце"
      },
      {
        "Номер строки": 1320,
        "Роль": "Скучно, пустота жизни страшная"
      },
      {
        "Номер строки": 1409,
        "Роль": "Отсутствие хандры"
      },
      {
        "Номер строки": 1826,
        "Роль": "Внутренняя осень и уныние"
      }
    ]
  },
  {
    "Тип": "Состояние здоровья",
    "Имя": "Сон",
    "Описание": "Качество и продолжительность сна.",
    "Упоминания": [
      {
        "Номер строки": 425,
        "Роль": "Сон 6 часов"
      },
      {
        "Номер строки": 445,
        "Роль": "Крепкий сон"
      },
      {
        "Номер строки": 477,
        "Роль": "Клонило в сон весь день"
      },
      {
        "Номер строки": 488,
        "Роль": "Ранний отход ко сну"
      },
      {
        "Номер строки": 504,
        "Роль": "Тяжелая дремота по утру не являлась"
      },
      {
        "Номер строки": 637,
        "Роль": "Хороший сон, очень хорошее пробуждение"
      },
      {
        "Номер строки": 712,
        "Роль": "Крепкий сон"
      },
      {
        "Номер строки": 1037,
        "Роль": "Плохой сон"
      },
      {
        "Номер строки": 1199,
        "Роль": "Хороший сон"
      },
      {
        "Номер строки": 1246,
        "Роль": "Хороший сон"
      },
      {
        "Номер строки": 1254,
        "Роль": "Хороший сон"
      },
      {
        "Номер строки": 1298,
        "Роль": "Хороший сон"
      },
      {
        "Номер строки": 1318,
        "Роль": "Хороший сон"
      },
      {
        "Номер строки": 1349,
        "Роль": "Хороший сон"
      },
      {
        "Номер строки": 1510,
        "Роль": "Отличный сон"
      },
      {
        "Номер строки": 1853,
        "Роль": "Отличный сон"
      },
      {
        "Номер строки": 1882,
        "Роль": "Отличный сон"
      },
      {
        "Номер строки": 1893,
        "Роль": "Отличный сон"
      }
    ]
  },
  {
    "Тип": "Состояние здоровья",
    "Имя": "Аппетит",
    "Описание": "Желание есть, оценка аппетита.",
    "Упоминания": [
      {
        "Номер строки": 484,
        "Роль": "Поправление аппетита от купания"
      },
      {
        "Номер строки": 876,
        "Роль": "Улучшение аппетита"
      },
      {
        "Номер строки": 1013,
        "Роль": "Пропажа аппетита"
      },
      {
        "Номер строки": 1319,
        "Роль": "Хороший аппетит"
      },
      {
        "Номер строки": 1461,
        "Роль": "Упавший аппетит"
      },
      {
        "Номер строки": 1524,
        "Роль": "Хороший аппетит"
      },
      {
        "Номер строки": 1817,
        "Роль": "Хороший аппетит"
      }
    ]
  },
  {
    "Тип": "Состояние здоровья",
    "Имя": "Вес тела",
    "Описание": "Изменения массы тела автора.",
    "Упоминания": [
      {
        "Номер строки": 655,
        "Роль": "Появление брюха"
      },
      {
        "Номер строки": 818,
        "Роль": "Вес 4 пуда 27 фунтов, приобретение трех фунтов за лето"
      },
      {
        "Номер строки": 851,
        "Роль": "Прибавка в весе от плотничества"
      },
      {
        "Номер строки": 860,
        "Роль": "Прибытие в весе 4 фунта"
      },
      {
        "Номер строки": 1254,
        "Роль": "Пополнение"
      },
      {
        "Номер строки": 1467,
        "Роль": "Значительное пополнение"
      },
      {
        "Номер строки": 1487,
        "Роль": "Много пополнел за несколько дней"
      },
      {
        "Номер строки": 1821,
        "Роль": "Заметное похудение"
      },
      {
        "Номер строки": 1900,
        "Роль": "Пополнение лица"
      }
    ]
  },
  {
    "Тип": "Состояние здоровья",
    "Имя": "Температура тела (Pf)",
    "Описание": "Показания термометра, вероятно, измеряемые утром или вечером, как индикатор состояния.",
    "Упоминания": [
      {
        "Номер строки": 378,
        "Роль": "Утренняя температура 80°"
      },
      {
        "Номер строки": 385,
        "Роль": "Температура 90°"
      },
      {
        "Номер строки": 389,
        "Роль": "Температура 80° в полдень"
      },
      {
        "Номер строки": 419,
        "Роль": "Утренняя температура 45°"
      },
      {
        "Номер строки": 435,
        "Роль": "Температура 30°"
      },
      {
        "Номер строки": 445,
        "Роль": "Ночная температура 80°"
      },
      {
        "Номер строки": 468,
        "Роль": "Температура 90°"
      },
      {
        "Номер строки": 562,
        "Роль": "Температура 60°"
      },
      {
        "Номер строки": 604,
        "Роль": "Плохая температура"
      },
      {
        "Номер строки": 648,
        "Роль": "Утренняя температура 60°"
      },
      {
        "Номер строки": 669,
        "Роль": "Вечерняя температура 60°"
      },
      {
        "Номер строки": 678,
        "Роль": "Температура 90°"
      },
      {
        "Номер строки": 689,
        "Роль": "Температура 80°"
      },
      {
        "Номер строки": 691,
        "Роль": "Хорошая температура"
      },
      {
        "Номер строки": 730,
        "Роль": "Температура 100°"
      },
      {
        "Номер строки": 794,
        "Роль": "Весьма хорошая температура"
      },
      {
        "Номер строки": 804,
        "Роль": "Температура 100°"
      },
      {
        "Номер строки": 837,
        "Роль": "Температура 90° каждую ночь"
      },
      {
        "Номер строки": 900,
        "Роль": "Ночная температура 80°"
      },
      {
        "Номер строки": 928,
        "Роль": "Температура 90°"
      },
      {
        "Номер строки": 1193,
        "Роль": "Температура 80°"
      },
      {
        "Номер строки": 1199,
        "Роль": "Температура 100° всю ночь"
      },
      {
        "Номер строки": 1342,
        "Роль": "Дневная и ночная температура 100°"
      },
      {
        "Номер строки": 1474,
        "Роль": "Температура 90° и 100° несколько ночей сряду"
      },
      {
        "Номер строки": 1489,
        "Роль": "Утренняя температура 100°"
      },
      {
        "Номер строки": 1490,
        "Роль": "Дневная температура 100°"
      },
      {
        "Номер строки": 1508,
        "Роль": "Температура 100°"
      },
      {
        "Номер строки": 1777,
        "Роль": "Температура до 90°"
      },
      {
        "Номер строки": 1880,
        "Роль": "Температура 100°"
      }
    ]
  }
]